setup.py
gitTree/__init__.py
gitTree/gitTree.py
git_tree.egg-info/PKG-INFO
git_tree.egg-info/SOURCES.txt
git_tree.egg-info/dependency_links.txt
git_tree.egg-info/entry_points.txt
git_tree.egg-info/top_level.txt