Metadata-Version: 1.1
Name: git-tree
Version: 0.1.1
Summary: List contents of git in a tree-like format
Home-page: https://github.com/kosystem/git-tree
Author: Kazufumi Onuma
Author-email: k.o.system2@gmail.com
License: MIT License
Platform: UNKNOWN
Classifier: Development Status :: 4 - Beta
Classifier: License :: OSI Approved :: MIT License
Classifier: Programming Language :: Python
Classifier: Topic :: Software Development
